<?xml version="1.0" encoding="UTF-8"?><?xml-stylesheet type='text/xsl' href='_UpgradeReport_Files/UpgradeReport.xslt'?><UpgradeLog>
<Properties><Property Name="Solution" Value="CatchMeGame">
</Property><Property Name="Solution File" Value="C:\Users\Owner\Documents\Polar Semiconductor Inc\CatchMeGame\CatchMeGame.sln">
</Property><Property Name="User Options File" Value="C:\Users\Owner\Documents\Polar Semiconductor Inc\CatchMeGame\CatchMeGame.suo">
</Property><Property Name="Date" Value="Wednesday, August 17, 2011">
</Property><Property Name="Time" Value="20:01 PM">
</Property></Properties><Event ErrorLevel="0" Project="" Source="CatchMeGame.sln" Description="File successfully backed up as C:\Users\Owner\Documents\Polar Semiconductor Inc\CatchMeGame\Backup\CatchMeGame.sln">
</Event><Event ErrorLevel="0" Project="" Source="CatchMeGame.suo" Description="File successfully backed up as C:\Users\Owner\Documents\Polar Semiconductor Inc\CatchMeGame\Backup\CatchMeGame.suo">
</Event><Event ErrorLevel="0" Project="CatchMeGame" Source="CatchMeGame\CatchMeGame.vbproj" Description="Project file successfully backed up as C:\Users\Owner\Documents\Polar Semiconductor Inc\CatchMeGame\Backup\CatchMeGame\CatchMeGame.vbproj">
</Event><Event ErrorLevel="0" Project="CatchMeGame" Source="CatchMeGame\CatchMeGame.vbproj.user" Description="Project user file successfully backed up as C:\Users\Owner\Documents\Polar Semiconductor Inc\CatchMeGame\Backup\CatchMeGame\CatchMeGame.vbproj.user">
</Event><Event ErrorLevel="0" Project="CatchMeGame" Source="CatchMeGame\Form1.vb" Description="File successfully backed up as C:\Users\Owner\Documents\Polar Semiconductor Inc\CatchMeGame\Backup\CatchMeGame\Form1.vb">
</Event><Event ErrorLevel="0" Project="CatchMeGame" Source="CatchMeGame\Form1.Designer.vb" Description="File successfully backed up as C:\Users\Owner\Documents\Polar Semiconductor Inc\CatchMeGame\Backup\CatchMeGame\Form1.Designer.vb">
</Event><Event ErrorLevel="0" Project="CatchMeGame" Source="CatchMeGame\My Project\AssemblyInfo.vb" Description="File successfully backed up as C:\Users\Owner\Documents\Polar Semiconductor Inc\CatchMeGame\Backup\CatchMeGame\My Project\AssemblyInfo.vb">
</Event><Event ErrorLevel="0" Project="CatchMeGame" Source="CatchMeGame\My Project\Application.Designer.vb" Description="File successfully backed up as C:\Users\Owner\Documents\Polar Semiconductor Inc\CatchMeGame\Backup\CatchMeGame\My Project\Application.Designer.vb">
</Event><Event ErrorLevel="0" Project="CatchMeGame" Source="CatchMeGame\My Project\Resources.Designer.vb" Description="File successfully backed up as C:\Users\Owner\Documents\Polar Semiconductor Inc\CatchMeGame\Backup\CatchMeGame\My Project\Resources.Designer.vb">
</Event><Event ErrorLevel="0" Project="CatchMeGame" Source="CatchMeGame\My Project\Settings.Designer.vb" Description="File successfully backed up as C:\Users\Owner\Documents\Polar Semiconductor Inc\CatchMeGame\Backup\CatchMeGame\My Project\Settings.Designer.vb">
</Event><Event ErrorLevel="0" Project="CatchMeGame" Source="CatchMeGame\My Project\Application.myapp" Description="File successfully backed up as C:\Users\Owner\Documents\Polar Semiconductor Inc\CatchMeGame\Backup\CatchMeGame\My Project\Application.myapp">
</Event><Event ErrorLevel="0" Project="CatchMeGame" Source="CatchMeGame\My Project\Settings.settings" Description="File successfully backed up as C:\Users\Owner\Documents\Polar Semiconductor Inc\CatchMeGame\Backup\CatchMeGame\My Project\Settings.settings">
</Event><Event ErrorLevel="0" Project="CatchMeGame" Source="CatchMeGame\Form1.resx" Description="File successfully backed up as C:\Users\Owner\Documents\Polar Semiconductor Inc\CatchMeGame\Backup\CatchMeGame\Form1.resx">
</Event><Event ErrorLevel="0" Project="CatchMeGame" Source="CatchMeGame\My Project\Resources.resx" Description="File successfully backed up as C:\Users\Owner\Documents\Polar Semiconductor Inc\CatchMeGame\Backup\CatchMeGame\My Project\Resources.resx">
</Event><Event ErrorLevel="0" Project="CatchMeGame" Source="CatchMeGame\CatchMeGame.vbproj" Description="Project converted successfully">
</Event><Event ErrorLevel="3" Project="CatchMeGame" Source="CatchMeGame\CatchMeGame.vbproj" Description="Converted">
</Event><Event ErrorLevel="0" Project="" Source="CatchMeGame.sln" Description="Solution converted successfully">
</Event><Event ErrorLevel="3" Project="" Source="CatchMeGame.sln" Description="Converted">
</Event><Event ErrorLevel="0" Project="CatchMeGame" Source="CatchMeGame\CatchMeGame.vbproj" Description="Scan complete: Upgrade not required for project files.">
</Event></UpgradeLog>